{
  "project_info": {
    "project_number": "880863204158",
    "project_id": "qrventory-b0ea6",
    "storage_bucket": "qrventory-b0ea6.firebasestorage.app"
  },
  "client": [
    {
      "client_info": {
        "mobilesdk_app_id": "1:880863204158:android:ec507d171cbedc3ac2126f",
        "android_client_info": {
          "package_name": "com.example.qrventory"
        }
      },
      "oauth_client": [],
      "api_key": [
        {
          "current_key": "AIzaSyCr9DUMeZ7D2ii9Be40ITSLLYHjqNBZsfs"
        }
      ],
      "services": {
        "appinvite_service": {
          "other_platform_oauth_client": []
        }
      }
    }
  ],
  "configuration_version": "1"
}